{
  "Dyastolic_Pressure -\u003e mqtt:topic:651b266b7b:2ff4d7742b:Dyastolic_Pressure_channel": {
    "class": "org.openhab.core.thing.link.ItemChannelLink",
    "value": {
      "channelUID": {
        "segments": [
          "mqtt",
          "topic",
          "651b266b7b",
          "2ff4d7742b",
          "Dyastolic_Pressure_channel"
        ],
        "uid": "mqtt:topic:651b266b7b:2ff4d7742b:Dyastolic_Pressure_channel"
      },
      "configuration": {
        "properties": {}
      },
      "itemName": "Dyastolic_Pressure"
    }
  },
  "Heart_Rate -\u003e mqtt:topic:651b266b7b:2ff4d7742b:heartRate_channel": {
    "class": "org.openhab.core.thing.link.ItemChannelLink",
    "value": {
      "channelUID": {
        "segments": [
          "mqtt",
          "topic",
          "651b266b7b",
          "2ff4d7742b",
          "heartRate_channel"
        ],
        "uid": "mqtt:topic:651b266b7b:2ff4d7742b:heartRate_channel"
      },
      "configuration": {
        "properties": {}
      },
      "itemName": "Heart_Rate"
    }
  },
  "Systolic_Pressure -\u003e mqtt:topic:651b266b7b:2ff4d7742b:Systolic_Pressure_channel": {
    "class": "org.openhab.core.thing.link.ItemChannelLink",
    "value": {
      "channelUID": {
        "segments": [
          "mqtt",
          "topic",
          "651b266b7b",
          "2ff4d7742b",
          "Systolic_Pressure_channel"
        ],
        "uid": "mqtt:topic:651b266b7b:2ff4d7742b:Systolic_Pressure_channel"
      },
      "configuration": {
        "properties": {}
      },
      "itemName": "Systolic_Pressure"
    }
  }
}